{
  "0": {
    "primary": [
      "TEXAS-DAVIS ROE"
    ],
    "extras": [],
    "offense": "Brooms Up",
    "time": "0000",
    "secondary": [
      "TEXAS-TATE KAY"
    ],
    "result": "BU",
    "period": "FLOOR"
  },
  "1": {
    "primary": [
      "TEXAS-LUKE MEISSNER"
    ],
    "time": "0005",
    "result": "EP",
    "offense": "TEXAS",
    "defense": "TAMU",
    "secondary": [
      "TEXAS-KASYE BEVERS"
    ],
    "extras": [],
    "period": "FLOOR"
  },
  "2": {
    "primary": [
      "TAMU-LOUIS SANCHEZ"
    ],
    "time": "0018",
    "result": "G",
    "offense": "TAMU",
    "defense": "TEXAS",
    "secondary": [
      "TAMU-CONNOR MCINTYRE"
    ],
    "extras": [
      [
        "Y",
        "TEXAS-JACK WANG"
      ],
      [
        "Y",
        "TAMU-NICK ROY"
      ]
    ],
    "period": "FLOOR"
  },
  "3": {
    "primary": [
      "TEXAS-LUKE MEISSNER"
    ],
    "time": "0043",
    "result": "GS",
    "offense": "TEXAS",
    "defense": "TAMU",
    "secondary": [],
    "extras": [],
    "period": "FLOOR"
  },
  "4": {
    "primary": [
      "TEXAS-DAVID HUBER"
    ],
    "time": "0109",
    "result": "TB",
    "offense": "TAMU",
    "defense": "TEXAS",
    "secondary": [
      "TAMU-HAYDAN ALTMAN"
    ],
    "extras": [],
    "period": "FLOOR"
  },
  "5": {
    "primary": [
      "TEXAS-DAVIS ROE"
    ],
    "time": "0208",
    "result": "GP",
    "offense": "TEXAS",
    "defense": "TAMU",
    "secondary": [
      "TEXAS-LUKE MEISSNER"
    ],
    "extras": [],
    "period": "FLOOR"
  },
  "6": {
    "primary": [
      "TAMU-CONNOR MCINTYRE"
    ],
    "time": "0249",
    "result": "EP",
    "offense": "TAMU",
    "defense": "TEXAS",
    "secondary": [
      "TAMU-HAYDAN ALTMAN"
    ],
    "extras": [],
    "period": "FLOOR"
  },
  "7": {
    "primary": [
      "TEXAS-DAVIS ROE"
    ],
    "time": "0334",
    "result": "GS",
    "offense": "TEXAS",
    "defense": "TAMU",
    "secondary": [
      "TEXAS-JOEY CASTELLANO"
    ],
    "extras": [],
    "period": "FLOOR"
  },
  "8": {
    "primary": [
      "TEXAS-JOEY CASTELLANO"
    ],
    "time": "0359",
    "result": "TD",
    "offense": "TAMU",
    "defense": "TEXAS",
    "secondary": [
      "TAMU-LOUIS SANCHEZ",
      "TAMU-HAYDAN ALTMAN"
    ],
    "extras": [],
    "period": "FLOOR"
  },
  "9": {
    "primary": [
      "TAMU-HAYDAN ALTMAN"
    ],
    "time": "0404",
    "result": "TC",
    "offense": "TEXAS",
    "defense": "TAMU",
    "secondary": [
      "TEXAS-JOEY CASTELLANO"
    ],
    "extras": [],
    "period": "FLOOR"
  },
  "10": {
    "primary": [
      "TAMU-LOUIS SANCHEZ"
    ],
    "time": "0425",
    "result": "GD",
    "offense": "TAMU",
    "defense": "TEXAS",
    "secondary": [],
    "extras": [],
    "period": "FLOOR"
  },
  "11": {
    "primary": [
      "TAMU-NICK ROY"
    ],
    "time": "0503",
    "result": "TB",
    "offense": "TEXAS",
    "defense": "TAMU",
    "secondary": [
      "TEXAS-JOEY CASTELLANO"
    ],
    "extras": [],
    "period": "FLOOR"
  },
  "12": {
    "primary": [
      "TAMU-HAYDAN ALTMAN"
    ],
    "time": "0516",
    "result": "GD",
    "offense": "TAMU",
    "defense": "TEXAS",
    "secondary": [],
    "extras": [],
    "period": "FLOOR"
  },
  "13": {
    "primary": [
      "TEXAS-JOSH JOHNSON"
    ],
    "time": "0553",
    "result": "GD",
    "offense": "TEXAS",
    "defense": "TAMU",
    "secondary": [],
    "extras": [],
    "period": "FLOOR"
  },
  "14": {
    "primary": [
      "TAMU-LOUIS SANCHEZ"
    ],
    "time": "0634",
    "result": "GS",
    "offense": "TAMU",
    "defense": "TEXAS",
    "secondary": [],
    "extras": [],
    "period": "FLOOR"
  },
  "15": {
    "primary": [
      "TEXAS-JOSH JOHNSON"
    ],
    "time": "0709",
    "result": "GD",
    "offense": "TEXAS",
    "defense": "TAMU",
    "secondary": [],
    "extras": [
      [
        "Y",
        "TAMU-KODY FOX"
      ]
    ],
    "period": "FLOOR"
  },
  "16": {
    "primary": [
      "TEXAS-JOHN ANDERSON"
    ],
    "time": "0730",
    "result": "TD",
    "offense": "TAMU",
    "defense": "TEXAS",
    "secondary": [
      "TAMU-LOUIS SANCHEZ",
      "TAMU-UNK"
    ],
    "extras": [],
    "period": "FLOOR"
  },
  "17": {
    "primary": [
      "TEXAS-JOSH JOHNSON"
    ],
    "time": "0738",
    "result": "GP",
    "offense": "TEXAS",
    "defense": "TAMU",
    "secondary": [
      "TEXAS-JOHN ANDERSON"
    ],
    "extras": [],
    "period": "FLOOR"
  },
  "18": {
    "primary": [
      "TEXAS-OLIVE JIM-DANIELS"
    ],
    "time": "0803",
    "result": "TC",
    "offense": "TAMU",
    "defense": "TEXAS",
    "secondary": [
      "TAMU-KODY FOX"
    ],
    "extras": [
      [
        "Y",
        "TAMU-MIGUEL SOBARZO"
      ]
    ],
    "period": "FLOOR"
  },
  "19": {
    "primary": [
      "TEXAS-MICHAEL JOHNSTON"
    ],
    "time": "0815",
    "result": "GP",
    "offense": "TEXAS",
    "defense": "TAMU",
    "secondary": [
      "TEXAS-JOHN ANDERSON"
    ],
    "extras": [],
    "period": "FLOOR"
  },
  "20": {
    "primary": [
      "TAMU-JESSICA HEMBREE"
    ],
    "time": "0846",
    "result": "EM",
    "offense": "TAMU",
    "defense": "TEXAS",
    "secondary": [],
    "extras": [],
    "period": "FLOOR"
  },
  "21": {
    "primary": [
      "TEXAS-MICHAEL JOHNSTON"
    ],
    "time": "0855",
    "result": "EM",
    "offense": "TEXAS",
    "defense": "TAMU",
    "secondary": [],
    "extras": [],
    "period": "FLOOR"
  },
  "22": {
    "primary": [
      "TEXAS-SETH LAPRAY"
    ],
    "time": "0911",
    "result": "TL",
    "offense": "TAMU",
    "defense": "TEXAS",
    "secondary": [
      "TAMU-NATHON SANCHEZ"
    ],
    "extras": [],
    "period": "FLOOR"
  },
  "23": {
    "primary": [
      "TEXAS-GRAYSON BRIGGS"
    ],
    "time": "0932",
    "result": "GD",
    "offense": "TEXAS",
    "defense": "TAMU",
    "secondary": [
      "TEXAS-NATHAN LEWIS"
    ],
    "extras": [],
    "period": "FLOOR"
  },
  "24": {
    "primary": [
      "TEXAS-TATE KAY"
    ],
    "time": "1006",
    "result": "TB",
    "offense": "TAMU",
    "defense": "TEXAS",
    "secondary": [
      "TAMU-KODY FOX"
    ],
    "extras": [
      [
        "R",
        "TEXAS-TATE KAY"
      ]
    ],
    "period": "FLOOR"
  },
  "25": {
    "primary": [
      "TEXAS-SETH LAPRAY"
    ],
    "time": "1018",
    "result": "GD",
    "offense": "TEXAS",
    "defense": "TAMU",
    "secondary": [],
    "extras": [],
    "period": "FLOOR"
  },
  "26": {
    "primary": [
      "TAMU-HAYDAN ALTMAN"
    ],
    "time": "1047",
    "result": "EP",
    "offense": "TAMU",
    "defense": "TEXAS",
    "secondary": [
      "TAMU-ADRIENNE DEMOSS"
    ],
    "extras": [],
    "period": "FLOOR"
  },
  "27": {
    "primary": [
      "TEXAS-GRAYSON BRIGGS"
    ],
    "time": "1111",
    "result": "GD",
    "offense": "TEXAS",
    "defense": "TAMU",
    "secondary": [],
    "extras": [],
    "period": "FLOOR"
  },
  "28": {
    "primary": [
      "TEXAS-TATE KAY"
    ],
    "time": "1131",
    "result": "TB",
    "offense": "TAMU",
    "defense": "TEXAS",
    "secondary": [
      "TAMU-HAYDAN ALTMAN"
    ],
    "extras": [],
    "period": "FLOOR"
  },
  "29": {
    "primary": [
      "TEXAS-GRAYSON BRIGGS"
    ],
    "time": "1138",
    "result": "GD",
    "offense": "TEXAS",
    "defense": "TAMU",
    "secondary": [],
    "extras": [],
    "period": "FLOOR"
  },
  "30": {
    "primary": [
      "TAMU-HAYDAN ALTMAN"
    ],
    "time": "1204",
    "result": "EM",
    "offense": "TAMU",
    "defense": "TEXAS",
    "secondary": [],
    "extras": [],
    "period": "FLOOR"
  },
  "31": {
    "primary": [
      "TAMU-ADRIENNE DEMOSS"
    ],
    "time": "1236",
    "result": "TD",
    "offense": "TEXAS",
    "defense": "TAMU",
    "secondary": [
      "TEXAS-CARLY JORDAN",
      "TEXAS-SETH LAPRAY"
    ],
    "extras": [],
    "period": "FLOOR"
  },
  "32": {
    "primary": [
      "TAMU-RANDI DORAN"
    ],
    "time": "1303",
    "result": "ED",
    "offense": "TAMU",
    "defense": "TEXAS",
    "secondary": [
      "TAMU-HAYDAN ALTMAN"
    ],
    "extras": [],
    "period": "FLOOR"
  },
  "33": {
    "primary": [
      "TAMU-HAYDAN ALTMAN"
    ],
    "time": "1310",
    "result": "TC",
    "offense": "TEXAS",
    "defense": "TAMU",
    "secondary": [
      "TEXAS-NATHAN LEWIS"
    ],
    "extras": [],
    "period": "FLOOR"
  },
  "34": {
    "primary": [
      "TEXAS-NATHAN LEWIS"
    ],
    "time": "1345",
    "result": "TL",
    "offense": "TAMU",
    "defense": "TEXAS",
    "secondary": [
      "TAMU-NATHON SANCHEZ"
    ],
    "extras": [],
    "period": "FLOOR"
  },
  "35": {
    "primary": [
      "TEXAS-KASYE BEVERS"
    ],
    "time": "1413",
    "result": "GD",
    "offense": "TEXAS",
    "defense": "TAMU",
    "secondary": [],
    "extras": [],
    "period": "FLOOR"
  },
  "36": {
    "primary": [
      "TAMU-HAYDAN ALTMAN"
    ],
    "time": "1452",
    "result": "EM",
    "offense": "TAMU",
    "defense": "TEXAS",
    "secondary": [],
    "extras": [],
    "period": "FLOOR"
  },
  "37": {
    "primary": [
      "TEXAS-KASYE BEVERS"
    ],
    "time": "1519",
    "result": "GP",
    "offense": "TEXAS",
    "defense": "TAMU",
    "secondary": [
      "TEXAS-JAYDAN GILSTRAP"
    ],
    "extras": [],
    "period": "FLOOR"
  },
  "38": {
    "primary": [
      "TEXAS-JACK WANG"
    ],
    "time": "1544",
    "result": "TB",
    "offense": "TAMU",
    "defense": "TEXAS",
    "secondary": [
      "TAMU-HAYDAN ALTMAN"
    ],
    "extras": [],
    "period": "FLOOR"
  },
  "39": {
    "primary": [
      "TEXAS-JAYDAN GILSTRAP"
    ],
    "time": "1603",
    "result": "EP",
    "offense": "TEXAS",
    "defense": "TAMU",
    "secondary": [
      "TEXAS-KASYE BEVERS"
    ],
    "extras": [],
    "period": "FLOOR"
  },
  "40": {
    "primary": [
      "TAMU-23"
    ],
    "time": "1631",
    "result": "GP",
    "offense": "TAMU",
    "defense": "TEXAS",
    "secondary": [
      "TAMU-CONNOR MCINTYRE"
    ],
    "extras": [
      [
        "1R",
        "TEXAS-JOSHUA MAGEE"
      ]
    ],
    "period": "FLOOR"
  },
  "41": {
    "primary": [
      "TAMU-ALEX STEWART"
    ],
    "time": "1816",
    "result": "TB",
    "offense": "TEXAS",
    "defense": "TAMU",
    "secondary": [
      "TEXAS-JAYDAN GILSTRAP"
    ],
    "extras": [
      [
        "2Y",
        "TAMU-NICK ROY"
      ]
    ],
    "period": "SOP"
  },
  "42": {
    "primary": [
      "TAMU-CONNOR MCINTYRE"
    ],
    "time": "1835",
    "result": "EP",
    "offense": "TAMU",
    "defense": "TEXAS",
    "secondary": [
      "TAMU-35"
    ],
    "extras": [],
    "period": "SOP"
  },
  "43": {
    "primary": [
      "TAMU-ALEX STEWART"
    ],
    "time": "1859",
    "result": "TB",
    "offense": "TEXAS",
    "defense": "TAMU",
    "secondary": [
      "TEXAS-LUKE MEISSNER"
    ],
    "extras": [],
    "period": "SOP"
  },
  "44": {
    "primary": [
      "TEXAS-OLIVE JIM-DANIELS"
    ],
    "time": "1922",
    "result": "TD",
    "offense": "TAMU",
    "defense": "TEXAS",
    "secondary": [
      "TAMU-CONNOR MCINTYRE",
      "TAMU-23"
    ],
    "extras": [],
    "period": "SOP"
  },
  "45": {
    "primary": [
      "TEXAS-OLIVE JIM-DANIELS"
    ],
    "time": "1929",
    "result": "GD",
    "offense": "TEXAS",
    "defense": "TAMU",
    "secondary": [],
    "extras": [],
    "period": "SOP"
  },
  "46": {
    "primary": [
      "TAMU-35"
    ],
    "time": "1953",
    "result": "EM",
    "offense": "TAMU",
    "defense": "TEXAS",
    "secondary": [],
    "extras": [],
    "period": "SOP"
  },
  "47": {
    "primary": [
      "TAMU-CONNOR MCINTYRE"
    ],
    "time": "2009",
    "result": "TD",
    "offense": "TEXAS",
    "defense": "TAMU",
    "secondary": [
      "TEXAS-LUKE MEISSNER",
      "TEXAS-OLIVE JIM-DANIELS"
    ],
    "extras": [],
    "period": "SOP"
  },
  "48": {
    "primary": [
      "TEXAS-KYLIE MCBRIDE"
    ],
    "time": "2039",
    "result": "TB",
    "offense": "TAMU",
    "defense": "TEXAS",
    "secondary": [
      "TAMU-35"
    ],
    "extras": [],
    "period": "SOP"
  },
  "49": {
    "primary": [
      "TEXAS-JOSH JOHNSON"
    ],
    "time": "2052",
    "result": "GP",
    "offense": "TEXAS",
    "defense": "TAMU",
    "secondary": [
      "TEXAS-LUKE MEISSNER"
    ],
    "extras": [],
    "period": "SOP"
  },
  "50": {
    "primary": [
      "TAMU-CONNOR MCINTYRE"
    ],
    "time": "2111",
    "result": "EM",
    "offense": "TAMU",
    "defense": "TEXAS",
    "secondary": [],
    "extras": [],
    "period": "SOP"
  },
  "51": {
    "primary": [
      "TEXAS-NATHAN LEWIS"
    ],
    "time": "2128",
    "result": "EM",
    "offense": "TEXAS",
    "defense": "TAMU",
    "secondary": [],
    "extras": [],
    "period": "SOP"
  },
  "52": {
    "primary": [
      "TAMU-CAMERON VILLAMIL"
    ],
    "time": "2159",
    "result": "EM",
    "offense": "TAMU",
    "defense": "TEXAS",
    "secondary": [],
    "extras": [],
    "period": "SOP"
  },
  "53": {
    "primary": [
      "TEXAS-LUKE MEISSNER"
    ],
    "time": "2231",
    "result": "GP",
    "offense": "TEXAS",
    "defense": "TAMU",
    "secondary": [
      "TEXAS-MICHAEL JOHNSTON"
    ],
    "extras": [],
    "period": "SOP"
  },
  "54": {
    "primary": [
      "TAMU-LANDIS WALTHER"
    ],
    "time": "2335",
    "result": "GP",
    "offense": "TAMU",
    "defense": "TEXAS",
    "secondary": [
      "TAMU-CAMERON VILLAMIL"
    ],
    "extras": [
      [
        "Y",
        "TEXAS-LUKE MEISSNER"
      ]
    ],
    "period": "SOP"
  },
  "55": {
    "primary": [
      "TAMU-34"
    ],
    "time": "2358",
    "result": "TB",
    "offense": "TEXAS",
    "defense": "TAMU",
    "secondary": [
      "TEXAS-JOSH JOHNSON"
    ],
    "extras": [],
    "period": "SOP"
  },
  "56": {
    "primary": [
      "TEXAS-UNK"
    ],
    "time": "2416",
    "result": "TC",
    "offense": "TAMU",
    "defense": "TEXAS",
    "secondary": [
      "TAMU-UNK"
    ],
    "extras": [],
    "period": "SOP"
  },
  "57": {
    "primary": [
      "TEXAS-DAVIS ROE"
    ],
    "time": "2453",
    "result": "GP",
    "offense": "TEXAS",
    "defense": "TAMU",
    "secondary": [
      "TEXAS-MICHAEL JOHNSTON"
    ],
    "extras": [],
    "period": "SOP"
  },
  "58": {
    "primary": [
      "TAMU-UNK"
    ],
    "time": "2522",
    "result": "G",
    "offense": "TAMU",
    "defense": "TEXAS",
    "secondary": [],
    "extras": [],
    "period": "SOP"
  },
  "59": {
    "primary": [
      "TEXAS-NATHAN LEWIS"
    ],
    "time": "2536",
    "result": "EM",
    "offense": "TEXAS",
    "defense": "TAMU",
    "secondary": [],
    "extras": [],
    "period": "SOP"
  },
  "60": {
    "primary": [
      "TAMU-LANDIS WALTHER"
    ],
    "time": "2613",
    "result": "G",
    "offense": "TAMU",
    "defense": "TEXAS",
    "secondary": [],
    "extras": [],
    "period": "SOP"
  },
  "61": {
    "primary": [
      "TEXAS-DAVIS ROE"
    ],
    "time": "2630",
    "result": "GD",
    "offense": "TEXAS",
    "defense": "TAMU",
    "secondary": [],
    "extras": [],
    "period": "SOP"
  },
  "62": {
    "primary": [
      "TEXAS-TATE KAY"
    ],
    "time": "2654",
    "result": "TB",
    "offense": "TAMU",
    "defense": "TEXAS",
    "secondary": [
      "TAMU-UNK"
    ],
    "extras": [],
    "period": "SOP"
  },
  "63": {
    "primary": [
      "TAMU-LOUIS SANCHEZ"
    ],
    "time": "2705",
    "result": "TC",
    "offense": "TEXAS",
    "defense": "TAMU",
    "secondary": [
      "TEXAS-NATHAN LEWIS"
    ],
    "extras": [],
    "period": "SOP"
  },
  "64": {
    "primary": [
      "TAMU-HAYDAN ALTMAN"
    ],
    "time": "2730",
    "result": "GD",
    "offense": "TAMU",
    "defense": "TEXAS",
    "secondary": [],
    "extras": [],
    "period": "SOP"
  }
}